{
	"start":	{
		"connected":	[{
				"socket":	5,
				"local_host":	"10.10.0.2",
				"local_port":	44812,
				"remote_host":	"10.10.0.1",
				"remote_port":	5201
			}],
		"version":	"iperf 3.9",
		"system_info":	"Linux ubuntu 5.15.0-171-generic #181-Ubuntu SMP Fri Feb 6 22:44:50 UTC 2026 x86_64",
		"timestamp":	{
			"time":	"Sat, 28 Mar 2026 06:45:48 GMT",
			"timesecs":	1774680348
		},
		"connecting_to":	{
			"host":	"10.10.0.1",
			"port":	5201
		},
		"cookie":	"cdhmlwxrxe4h5nk3lnftz7ybksioywvizhxi",
		"tcp_mss_default":	1368,
		"sock_bufsize":	0,
		"sndbuf_actual":	16384,
		"rcvbuf_actual":	131072,
		"test_start":	{
			"protocol":	"TCP",
			"num_streams":	1,
			"blksize":	131072,
			"omit":	0,
			"duration":	60,
			"bytes":	0,
			"blocks":	0,
			"reverse":	0,
			"tos":	0
		}
	},
	"intervals":	[{
			"streams":	[{
					"socket":	5,
					"start":	0,
					"end":	1.000116,
					"seconds":	1.0001159906387329,
					"bytes":	6799488,
					"bits_per_second":	54389595.316098861,
					"retransmits":	93,
					"snd_cwnd":	584136,
					"rtt":	66008,
					"rttvar":	406,
					"pmtu":	1420,
					"omitted":	false,
					"sender":	true
				}],
			"sum":	{
				"start":	0,
				"end":	1.000116,
				"seconds":	1.0001159906387329,
				"bytes":	6799488,
				"bits_per_second":	54389595.316098861,
				"retransmits":	93,
				"omitted":	false,
				"sender":	true
			}
		}, {
			"streams":	[{
					"socket":	5,
					"start":	1.000116,
					"end":	2.000324,
					"seconds":	1.0002080202102661,
					"bytes":	6553600,
					"bits_per_second":	52417896.018248573,
					"retransmits":	11,
					"snd_cwnd":	447336,
					"rtt":	75048,
					"rttvar":	2948,
					"pmtu":	1420,
					"omitted":	false,
					"sender":	true
				}],
			"sum":	{
				"start":	1.000116,
				"end":	2.000324,
				"seconds":	1.0002080202102661,
				"bytes":	6553600,
				"bits_per_second":	52417896.018248573,
				"retransmits":	11,
				"omitted":	false,
				"sender":	true
			}
		}, {
			"streams":	[{
					"socket":	5,
					"start":	2.000324,
					"end":	3.000278,
					"seconds":	0.9999539852142334,
					"bytes":	5242880,
					"bits_per_second":	41944970.088812627,
					"retransmits":	0,
					"snd_cwnd":	487008,
					"rtt":	82927,
					"rttvar":	3772,
					"pmtu":	1420,
					"omitted":	false,
					"sender":	true
				}],
			"sum":	{
				"start":	2.000324,
				"end":	3.000278,
				"seconds":	0.9999539852142334,
				"bytes":	5242880,
				"bits_per_second":	41944970.088812627,
				"retransmits":	0,
				"omitted":	false,
				"sender":	true
			}
		}, {
			"streams":	[{
					"socket":	5,
					"start":	3.000278,
					"end":	4.00022,
					"seconds":	0.99994200468063354,
					"bytes":	6553600,
					"bits_per_second":	52431840.801352248,
					"retransmits":	0,
					"snd_cwnd":	510264,
					"rtt":	69957,
					"rttvar":	698,
					"pmtu":	1420,
					"omitted":	false,
					"sender":	true
				}],
			"sum":	{
				"start":	3.000278,
				"end":	4.00022,
				"seconds":	0.99994200468063354,
				"bytes":	6553600,
				"bits_per_second":	52431840.801352248,
				"retransmits":	0,
				"omitted":	false,
				"sender":	true
			}
		}, {
			"streams":	[{
					"socket":	5,
					"start":	4.00022,
					"end":	5.000443,
					"seconds":	1.0002230405807495,
					"bytes":	6553600,
					"bits_per_second":	52417108.8575992,
					"retransmits":	0,
					"snd_cwnd":	523944,
					"rtt":	70717,
					"rttvar":	141,
					"pmtu":	1420,
					"omitted":	false,
					"sender":	true
				}],
			"sum":	{
				"start":	4.00022,
				"end":	5.000443,
				"seconds":	1.0002230405807495,
				"bytes":	6553600,
				"bits_per_second":	52417108.8575992,
				"retransmits":	0,
				"omitted":	false,
				"sender":	true
			}
		}, {
			"streams":	[{
					"socket":	5,
					"start":	5.000443,
					"end":	6.000715,
					"seconds":	1.0002720355987549,
					"bytes":	6553600,
					"bits_per_second":	52414541.378852539,
					"retransmits":	0,
					"snd_cwnd":	529416,
					"rtt":	71436,
					"rttvar":	962,
					"pmtu":	1420,
					"omitted":	false,
					"sender":	true
				}],
			"sum":	{
				"start":	5.000443,
				"end":	6.000715,
				"seconds":	1.0002720355987549,
				"bytes":	6553600,
				"bits_per_second":	52414541.378852539,
				"retransmits":	0,
				"omitted":	false,
				"sender":	true
			}
		}, {
			"streams":	[{
					"socket":	5,
					"start":	6.000715,
					"end":	7.000429,
					"seconds":	0.99971401691436768,
					"bytes":	6553600,
					"bits_per_second":	52443798.039185524,
					"retransmits":	0,
					"snd_cwnd":	529416,
					"rtt":	73390,
					"rttvar":	67,
					"pmtu":	1420,
					"omitted":	false,
					"sender":	true
				}],
			"sum":	{
				"start":	6.000715,
				"end":	7.000429,
				"seconds":	0.99971401691436768,
				"bytes":	6553600,
				"bits_per_second":	52443798.039185524,
				"retransmits":	0,
				"omitted":	false,
				"sender":	true
			}
		}, {
			"streams":	[{
					"socket":	5,
					"start":	7.000429,
					"end":	8.002571,
					"seconds":	1.0021419525146484,
					"bytes":	6553600,
					"bits_per_second":	52316740.027140655,
					"retransmits":	0,
					"snd_cwnd":	529416,
					"rtt":	70099,
					"rttvar":	1955,
					"pmtu":	1420,
					"omitted":	false,
					"sender":	true
				}],
			"sum":	{
				"start":	7.000429,
				"end":	8.002571,
				"seconds":	1.0021419525146484,
				"bytes":	6553600,
				"bits_per_second":	52316740.027140655,
				"retransmits":	0,
				"omitted":	false,
				"sender":	true
			}
		}, {
			"streams":	[{
					"socket":	5,
					"start":	8.002571,
					"end":	9.000539,
					"seconds":	0.997968018054962,
					"bytes":	6553600,
					"bits_per_second":	52535551.291697338,
					"retransmits":	0,
					"snd_cwnd":	532152,
					"rtt":	69751,
					"rttvar":	2133,
					"pmtu":	1420,
					"omitted":	false,
					"sender":	true
				}],
			"sum":	{
				"start":	8.002571,
				"end":	9.000539,
				"seconds":	0.997968018054962,
				"bytes":	6553600,
				"bits_per_second":	52535551.291697338,
				"retransmits":	0,
				"omitted":	false,
				"sender":	true
			}
		}, {
			"streams":	[{
					"socket":	5,
					"start":	9.000539,
					"end":	10.000599,
					"seconds":	1.000059962272644,
					"bytes":	6553600,
					"bits_per_second":	52425656.4384951,
					"retransmits":	0,
					"snd_cwnd":	540360,
					"rtt":	73257,
					"rttvar":	4514,
					"pmtu":	1420,
					"omitted":	false,
					"sender":	true
				}],
			"sum":	{
				"start":	9.000539,
				"end":	10.000599,
				"seconds":	1.000059962272644,
				"bytes":	6553600,
				"bits_per_second":	52425656.4384951,
				"retransmits":	0,
				"omitted":	false,
				"sender":	true
			}
		}, {
			"streams":	[{
					"socket":	5,
					"start":	10.000599,
					"end":	11.00061,
					"seconds":	1.0000109672546387,
					"bytes":	6553600,
					"bits_per_second":	52428225.0063061,
					"retransmits":	0,
					"snd_cwnd":	556776,
					"rtt":	70858,
					"rttvar":	1857,
					"pmtu":	1420,
					"omitted":	false,
					"sender":	true
				}],
			"sum":	{
				"start":	10.000599,
				"end":	11.00061,
				"seconds":	1.0000109672546387,
				"bytes":	6553600,
				"bits_per_second":	52428225.0063061,
				"retransmits":	0,
				"omitted":	false,
				"sender":	true
			}
		}, {
			"streams":	[{
					"socket":	5,
					"start":	11.00061,
					"end":	12.000755,
					"seconds":	1.0001449584960938,
					"bytes":	6553600,
					"bits_per_second":	52421201.1015249,
					"retransmits":	0,
					"snd_cwnd":	585504,
					"rtt":	76484,
					"rttvar":	565,
					"pmtu":	1420,
					"omitted":	false,
					"sender":	true
				}],
			"sum":	{
				"start":	11.00061,
				"end":	12.000755,
				"seconds":	1.0001449584960938,
				"bytes":	6553600,
				"bits_per_second":	52421201.1015249,
				"retransmits":	0,
				"omitted":	false,
				"sender":	true
			}
		}, {
			"streams":	[{
					"socket":	5,
					"start":	12.000755,
					"end":	13.001276,
					"seconds":	1.0005209445953369,
					"bytes":	6553600,
					"bits_per_second":	52401501.720890962,
					"retransmits":	0,
					"snd_cwnd":	629280,
					"rtt":	79073,
					"rttvar":	422,
					"pmtu":	1420,
					"omitted":	false,
					"sender":	true
				}],
			"sum":	{
				"start":	12.000755,
				"end":	13.001276,
				"seconds":	1.0005209445953369,
				"bytes":	6553600,
				"bits_per_second":	52401501.720890962,
				"retransmits":	0,
				"omitted":	false,
				"sender":	true
			}
		}, {
			"streams":	[{
					"socket":	5,
					"start":	13.001276,
					"end":	14.000903,
					"seconds":	0.99962699413299561,
					"bytes":	9175040,
					"bits_per_second":	73427708.9662451,
					"retransmits":	0,
					"snd_cwnd":	693576,
					"rtt":	70680,
					"rttvar":	148,
					"pmtu":	1420,
					"omitted":	false,
					"sender":	true
				}],
			"sum":	{
				"start":	13.001276,
				"end":	14.000903,
				"seconds":	0.99962699413299561,
				"bytes":	9175040,
				"bits_per_second":	73427708.9662451,
				"retransmits":	0,
				"omitted":	false,
				"sender":	true
			}
		}, {
			"streams":	[{
					"socket":	5,
					"start":	14.000903,
					"end":	15.009937,
					"seconds":	1.0090340375900269,
					"bytes":	7864320,
					"bits_per_second":	62351276.226781115,
					"retransmits":	90,
					"snd_cwnd":	536256,
					"rtt":	76227,
					"rttvar":	3365,
					"pmtu":	1420,
					"omitted":	false,
					"sender":	true
				}],
			"sum":	{
				"start":	14.000903,
				"end":	15.009937,
				"seconds":	1.0090340375900269,
				"bytes":	7864320,
				"bits_per_second":	62351276.226781115,
				"retransmits":	90,
				"omitted":	false,
				"sender":	true
			}
		}, {
			"streams":	[{
					"socket":	5,
					"start":	15.009937,
					"end":	16.00114,
					"seconds":	0.991203010082245,
					"bytes":	6553600,
					"bits_per_second":	52894108.943080924,
					"retransmits":	0,
					"snd_cwnd":	614232,
					"rtt":	72797,
					"rttvar":	5280,
					"pmtu":	1420,
					"omitted":	false,
					"sender":	true
				}],
			"sum":	{
				"start":	15.009937,
				"end":	16.00114,
				"seconds":	0.991203010082245,
				"bytes":	6553600,
				"bits_per_second":	52894108.943080924,
				"retransmits":	0,
				"omitted":	false,
				"sender":	true
			}
		}, {
			"streams":	[{
					"socket":	5,
					"start":	16.00114,
					"end":	17.000851,
					"seconds":	0.999710977077484,
					"bytes":	7864320,
					"bits_per_second":	62932749.007039972,
					"retransmits":	0,
					"snd_cwnd":	673056,
					"rtt":	72595,
					"rttvar":	1210,
					"pmtu":	1420,
					"omitted":	false,
					"sender":	true
				}],
			"sum":	{
				"start":	16.00114,
				"end":	17.000851,
				"seconds":	0.999710977077484,
				"bytes":	7864320,
				"bits_per_second":	62932749.007039972,
				"retransmits":	0,
				"omitted":	false,
				"sender":	true
			}
		}, {
			"streams":	[{
					"socket":	5,
					"start":	17.000851,
					"end":	18.000866,
					"seconds":	1.0000150203704834,
					"bytes":	6553600,
					"bits_per_second":	52428012.511828363,
					"retransmits":	0,
					"snd_cwnd":	715464,
					"rtt":	68435,
					"rttvar":	482,
					"pmtu":	1420,
					"omitted":	false,
					"sender":	true
				}],
			"sum":	{
				"start":	17.000851,
				"end":	18.000866,
				"seconds":	1.0000150203704834,
				"bytes":	6553600,
				"bits_per_second":	52428012.511828363,
				"retransmits":	0,
				"omitted":	false,
				"sender":	true
			}
		}, {
			"streams":	[{
					"socket":	5,
					"start":	18.000866,
					"end":	19.000192,
					"seconds":	0.99932599067688,
					"bytes":	9175040,
					"bits_per_second":	73449825.8674162,
					"retransmits":	0,
					"snd_cwnd":	742824,
					"rtt":	83123,
					"rttvar":	764,
					"pmtu":	1420,
					"omitted":	false,
					"sender":	true
				}],
			"sum":	{
				"start":	18.000866,
				"end":	19.000192,
				"seconds":	0.99932599067688,
				"bytes":	9175040,
				"bits_per_second":	73449825.8674162,
				"retransmits":	0,
				"omitted":	false,
				"sender":	true
			}
		}, {
			"streams":	[{
					"socket":	5,
					"start":	19.000192,
					"end":	20.001031,
					"seconds":	1.0008389949798584,
					"bytes":	6553600,
					"bits_per_second":	52384849.374354281,
					"retransmits":	38,
					"snd_cwnd":	552672,
					"rtt":	69620,
					"rttvar":	530,
					"pmtu":	1420,
					"omitted":	false,
					"sender":	true
				}],
			"sum":	{
				"start":	19.000192,
				"end":	20.001031,
				"seconds":	1.0008389949798584,
				"bytes":	6553600,
				"bits_per_second":	52384849.374354281,
				"retransmits":	38,
				"omitted":	false,
				"sender":	true
			}
		}, {
			"streams":	[{
					"socket":	5,
					"start":	20.001031,
					"end":	21.000406,
					"seconds":	0.99937498569488525,
					"bytes":	6553600,
					"bits_per_second":	52461589.2437464,
					"retransmits":	0,
					"snd_cwnd":	592344,
					"rtt":	69801,
					"rttvar":	995,
					"pmtu":	1420,
					"omitted":	false,
					"sender":	true
				}],
			"sum":	{
				"start":	20.001031,
				"end":	21.000406,
				"seconds":	0.99937498569488525,
				"bytes":	6553600,
				"bits_per_second":	52461589.2437464,
				"retransmits":	0,
				"omitted":	false,
				"sender":	true
			}
		}, {
			"streams":	[{
					"socket":	5,
					"start":	21.000406,
					"end":	22.000683,
					"seconds":	1.000277042388916,
					"bytes":	6553600,
					"bits_per_second":	52414279.022926182,
					"retransmits":	0,
					"snd_cwnd":	615600,
					"rtt":	76854,
					"rttvar":	3363,
					"pmtu":	1420,
					"omitted":	false,
					"sender":	true
				}],
			"sum":	{
				"start":	21.000406,
				"end":	22.000683,
				"seconds":	1.000277042388916,
				"bytes":	6553600,
				"bits_per_second":	52414279.022926182,
				"retransmits":	0,
				"omitted":	false,
				"sender":	true
			}
		}, {
			"streams":	[{
					"socket":	5,
					"start":	22.000683,
					"end":	23.000789,
					"seconds":	1.0001059770584106,
					"bytes":	6553600,
					"bits_per_second":	52423244.338772632,
					"retransmits":	19,
					"snd_cwnd":	467856,
					"rtt":	67663,
					"rttvar":	574,
					"pmtu":	1420,
					"omitted":	false,
					"sender":	true
				}],
			"sum":	{
				"start":	22.000683,
				"end":	23.000789,
				"seconds":	1.0001059770584106,
				"bytes":	6553600,
				"bits_per_second":	52423244.338772632,
				"retransmits":	19,
				"omitted":	false,
				"sender":	true
			}
		}, {
			"streams":	[{
					"socket":	5,
					"start":	23.000789,
					"end":	24.000407,
					"seconds":	0.99961799383163452,
					"bytes":	5242880,
					"bits_per_second":	41959068.623032868,
					"retransmits":	0,
					"snd_cwnd":	497952,
					"rtt":	71270,
					"rttvar":	3212,
					"pmtu":	1420,
					"omitted":	false,
					"sender":	true
				}],
			"sum":	{
				"start":	23.000789,
				"end":	24.000407,
				"seconds":	0.99961799383163452,
				"bytes":	5242880,
				"bits_per_second":	41959068.623032868,
				"retransmits":	0,
				"omitted":	false,
				"sender":	true
			}
		}, {
			"streams":	[{
					"socket":	5,
					"start":	24.000407,
					"end":	25.000543,
					"seconds":	1.0001360177993774,
					"bytes":	7864320,
					"bits_per_second":	62906003.663814016,
					"retransmits":	0,
					"snd_cwnd":	515736,
					"rtt":	68276,
					"rttvar":	1449,
					"pmtu":	1420,
					"omitted":	false,
					"sender":	true
				}],
			"sum":	{
				"start":	24.000407,
				"end":	25.000543,
				"seconds":	1.0001360177993774,
				"bytes":	7864320,
				"bits_per_second":	62906003.663814016,
				"retransmits":	0,
				"omitted":	false,
				"sender":	true
			}
		}, {
			"streams":	[{
					"socket":	5,
					"start":	25.000543,
					"end":	26.002382,
					"seconds":	1.0018390417099,
					"bytes":	6553600,
					"bits_per_second":	52332558.242606081,
					"retransmits":	0,
					"snd_cwnd":	523944,
					"rtt":	69705,
					"rttvar":	3104,
					"pmtu":	1420,
					"omitted":	false,
					"sender":	true
				}],
			"sum":	{
				"start":	25.000543,
				"end":	26.002382,
				"seconds":	1.0018390417099,
				"bytes":	6553600,
				"bits_per_second":	52332558.242606081,
				"retransmits":	0,
				"omitted":	false,
				"sender":	true
			}
		}, {
			"streams":	[{
					"socket":	5,
					"start":	26.002382,
					"end":	27.000375,
					"seconds":	0.997992992401123,
					"bytes":	6553600,
					"bits_per_second":	52534236.612081647,
					"retransmits":	0,
					"snd_cwnd":	525312,
					"rtt":	72888,
					"rttvar":	282,
					"pmtu":	1420,
					"omitted":	false,
					"sender":	true
				}],
			"sum":	{
				"start":	26.002382,
				"end":	27.000375,
				"seconds":	0.997992992401123,
				"bytes":	6553600,
				"bits_per_second":	52534236.612081647,
				"retransmits":	0,
				"omitted":	false,
				"sender":	true
			}
		}, {
			"streams":	[{
					"socket":	5,
					"start":	27.000375,
					"end":	28.000526,
					"seconds":	1.0001510381698608,
					"bytes":	6553600,
					"bits_per_second":	52420882.4458529,
					"retransmits":	0,
					"snd_cwnd":	525312,
					"rtt":	68893,
					"rttvar":	962,
					"pmtu":	1420,
					"omitted":	false,
					"sender":	true
				}],
			"sum":	{
				"start":	27.000375,
				"end":	28.000526,
				"seconds":	1.0001510381698608,
				"bytes":	6553600,
				"bits_per_second":	52420882.4458529,
				"retransmits":	0,
				"omitted":	false,
				"sender":	true
			}
		}, {
			"streams":	[{
					"socket":	5,
					"start":	28.000526,
					"end":	29.000474,
					"seconds":	0.999948024749756,
					"bytes":	6553600,
					"bits_per_second":	52431525.141639918,
					"retransmits":	0,
					"snd_cwnd":	525312,
					"rtt":	68952,
					"rttvar":	2023,
					"pmtu":	1420,
					"omitted":	false,
					"sender":	true
				}],
			"sum":	{
				"start":	28.000526,
				"end":	29.000474,
				"seconds":	0.999948024749756,
				"bytes":	6553600,
				"bits_per_second":	52431525.141639918,
				"retransmits":	0,
				"omitted":	false,
				"sender":	true
			}
		}, {
			"streams":	[{
					"socket":	5,
					"start":	29.000474,
					"end":	30.001236,
					"seconds":	1.0007619857788086,
					"bytes":	6553600,
					"bits_per_second":	52388880.418153666,
					"retransmits":	0,
					"snd_cwnd":	532152,
					"rtt":	66582,
					"rttvar":	440,
					"pmtu":	1420,
					"omitted":	false,
					"sender":	true
				}],
			"sum":	{
				"start":	29.000474,
				"end":	30.001236,
				"seconds":	1.0007619857788086,
				"bytes":	6553600,
				"bits_per_second":	52388880.418153666,
				"retransmits":	0,
				"omitted":	false,
				"sender":	true
			}
		}, {
			"streams":	[{
					"socket":	5,
					"start":	30.001236,
					"end":	31.000511,
					"seconds":	0.999275028705597,
					"bytes":	7864320,
					"bits_per_second":	62960204.34083686,
					"retransmits":	0,
					"snd_cwnd":	544464,
					"rtt":	70547,
					"rttvar":	1451,
					"pmtu":	1420,
					"omitted":	false,
					"sender":	true
				}],
			"sum":	{
				"start":	30.001236,
				"end":	31.000511,
				"seconds":	0.999275028705597,
				"bytes":	7864320,
				"bits_per_second":	62960204.34083686,
				"retransmits":	0,
				"omitted":	false,
				"sender":	true
			}
		}, {
			"streams":	[{
					"socket":	5,
					"start":	31.000511,
					"end":	32.00207,
					"seconds":	1.0015590190887451,
					"bytes":	6553600,
					"bits_per_second":	52347189.7319657,
					"retransmits":	0,
					"snd_cwnd":	567720,
					"rtt":	70280,
					"rttvar":	1395,
					"pmtu":	1420,
					"omitted":	false,
					"sender":	true
				}],
			"sum":	{
				"start":	31.000511,
				"end":	32.00207,
				"seconds":	1.0015590190887451,
				"bytes":	6553600,
				"bits_per_second":	52347189.7319657,
				"retransmits":	0,
				"omitted":	false,
				"sender":	true
			}
		}, {
			"streams":	[{
					"socket":	5,
					"start":	32.00207,
					"end":	33.001146,
					"seconds":	0.999076008796692,
					"bytes":	5242880,
					"bits_per_second":	41981830.842397146,
					"retransmits":	0,
					"snd_cwnd":	604656,
					"rtt":	85772,
					"rttvar":	2866,
					"pmtu":	1420,
					"omitted":	false,
					"sender":	true
				}],
			"sum":	{
				"start":	32.00207,
				"end":	33.001146,
				"seconds":	0.999076008796692,
				"bytes":	5242880,
				"bits_per_second":	41981830.842397146,
				"retransmits":	0,
				"omitted":	false,
				"sender":	true
			}
		}, {
			"streams":	[{
					"socket":	5,
					"start":	33.001146,
					"end":	34.000221,
					"seconds":	0.99907499551773071,
					"bytes":	7864320,
					"bits_per_second":	62972810.13163285,
					"retransmits":	0,
					"snd_cwnd":	659376,
					"rtt":	75693,
					"rttvar":	1114,
					"pmtu":	1420,
					"omitted":	false,
					"sender":	true
				}],
			"sum":	{
				"start":	33.001146,
				"end":	34.000221,
				"seconds":	0.99907499551773071,
				"bytes":	7864320,
				"bits_per_second":	62972810.13163285,
				"retransmits":	0,
				"omitted":	false,
				"sender":	true
			}
		}, {
			"streams":	[{
					"socket":	5,
					"start":	34.000221,
					"end":	35.00025,
					"seconds":	1.0000289678573608,
					"bytes":	7864320,
					"bits_per_second":	62912737.5527924,
					"retransmits":	0,
					"snd_cwnd":	734616,
					"rtt":	78242,
					"rttvar":	834,
					"pmtu":	1420,
					"omitted":	false,
					"sender":	true
				}],
			"sum":	{
				"start":	34.000221,
				"end":	35.00025,
				"seconds":	1.0000289678573608,
				"bytes":	7864320,
				"bits_per_second":	62912737.5527924,
				"retransmits":	0,
				"omitted":	false,
				"sender":	true
			}
		}, {
			"streams":	[{
					"socket":	5,
					"start":	35.00025,
					"end":	36.001192,
					"seconds":	1.00094199180603,
					"bytes":	6553600,
					"bits_per_second":	52379458.978837639,
					"retransmits":	5,
					"snd_cwnd":	584136,
					"rtt":	68857,
					"rttvar":	1081,
					"pmtu":	1420,
					"omitted":	false,
					"sender":	true
				}],
			"sum":	{
				"start":	35.00025,
				"end":	36.001192,
				"seconds":	1.00094199180603,
				"bytes":	6553600,
				"bits_per_second":	52379458.978837639,
				"retransmits":	5,
				"omitted":	false,
				"sender":	true
			}
		}, {
			"streams":	[{
					"socket":	5,
					"start":	36.001192,
					"end":	37.000284,
					"seconds":	0.9990919828414917,
					"bytes":	7864320,
					"bits_per_second":	62971739.419894375,
					"retransmits":	0,
					"snd_cwnd":	652536,
					"rtt":	87424,
					"rttvar":	1690,
					"pmtu":	1420,
					"omitted":	false,
					"sender":	true
				}],
			"sum":	{
				"start":	36.001192,
				"end":	37.000284,
				"seconds":	0.9990919828414917,
				"bytes":	7864320,
				"bits_per_second":	62971739.419894375,
				"retransmits":	0,
				"omitted":	false,
				"sender":	true
			}
		}, {
			"streams":	[{
					"socket":	5,
					"start":	37.000284,
					"end":	38.000157,
					"seconds":	0.99987298250198364,
					"bytes":	7864320,
					"bits_per_second":	62922552.265157521,
					"retransmits":	0,
					"snd_cwnd":	700416,
					"rtt":	67031,
					"rttvar":	378,
					"pmtu":	1420,
					"omitted":	false,
					"sender":	true
				}],
			"sum":	{
				"start":	37.000284,
				"end":	38.000157,
				"seconds":	0.99987298250198364,
				"bytes":	7864320,
				"bits_per_second":	62922552.265157521,
				"retransmits":	0,
				"omitted":	false,
				"sender":	true
			}
		}, {
			"streams":	[{
					"socket":	5,
					"start":	38.000157,
					"end":	39.000246,
					"seconds":	1.0000890493392944,
					"bytes":	9175040,
					"bits_per_second":	73393784.3319969,
					"retransmits":	0,
					"snd_cwnd":	733248,
					"rtt":	79220,
					"rttvar":	855,
					"pmtu":	1420,
					"omitted":	false,
					"sender":	true
				}],
			"sum":	{
				"start":	38.000157,
				"end":	39.000246,
				"seconds":	1.0000890493392944,
				"bytes":	9175040,
				"bits_per_second":	73393784.3319969,
				"retransmits":	0,
				"omitted":	false,
				"sender":	true
			}
		}, {
			"streams":	[{
					"socket":	5,
					"start":	39.000246,
					"end":	40.000172,
					"seconds":	0.999925971031189,
					"bytes":	9175040,
					"bits_per_second":	73405754.1522847,
					"retransmits":	0,
					"snd_cwnd":	752400,
					"rtt":	71696,
					"rttvar":	769,
					"pmtu":	1420,
					"omitted":	false,
					"sender":	true
				}],
			"sum":	{
				"start":	39.000246,
				"end":	40.000172,
				"seconds":	0.999925971031189,
				"bytes":	9175040,
				"bits_per_second":	73405754.1522847,
				"retransmits":	0,
				"omitted":	false,
				"sender":	true
			}
		}, {
			"streams":	[{
					"socket":	5,
					"start":	40.000172,
					"end":	41.000891,
					"seconds":	1.0007189512252808,
					"bytes":	9175040,
					"bits_per_second":	73347586.662697464,
					"retransmits":	0,
					"snd_cwnd":	761976,
					"rtt":	69809,
					"rttvar":	237,
					"pmtu":	1420,
					"omitted":	false,
					"sender":	true
				}],
			"sum":	{
				"start":	40.000172,
				"end":	41.000891,
				"seconds":	1.0007189512252808,
				"bytes":	9175040,
				"bits_per_second":	73347586.662697464,
				"retransmits":	0,
				"omitted":	false,
				"sender":	true
			}
		}, {
			"streams":	[{
					"socket":	5,
					"start":	41.000891,
					"end":	42.000633,
					"seconds":	0.99974197149276733,
					"bytes":	7864320,
					"bits_per_second":	62930797.939851381,
					"retransmits":	0,
					"snd_cwnd":	764712,
					"rtt":	86578,
					"rttvar":	297,
					"pmtu":	1420,
					"omitted":	false,
					"sender":	true
				}],
			"sum":	{
				"start":	41.000891,
				"end":	42.000633,
				"seconds":	0.99974197149276733,
				"bytes":	7864320,
				"bits_per_second":	62930797.939851381,
				"retransmits":	0,
				"omitted":	false,
				"sender":	true
			}
		}, {
			"streams":	[{
					"socket":	5,
					"start":	42.000633,
					"end":	43.000224,
					"seconds":	0.99959099292755127,
					"bytes":	7864320,
					"bits_per_second":	62940303.029080957,
					"retransmits":	0,
					"snd_cwnd":	764712,
					"rtt":	71766,
					"rttvar":	1032,
					"pmtu":	1420,
					"omitted":	false,
					"sender":	true
				}],
			"sum":	{
				"start":	42.000633,
				"end":	43.000224,
				"seconds":	0.99959099292755127,
				"bytes":	7864320,
				"bits_per_second":	62940303.029080957,
				"retransmits":	0,
				"omitted":	false,
				"sender":	true
			}
		}, {
			"streams":	[{
					"socket":	5,
					"start":	43.000224,
					"end":	44.00063,
					"seconds":	1.00040602684021,
					"bytes":	7864320,
					"bits_per_second":	62889025.367746048,
					"retransmits":	99,
					"snd_cwnd":	544464,
					"rtt":	71445,
					"rttvar":	1120,
					"pmtu":	1420,
					"omitted":	false,
					"sender":	true
				}],
			"sum":	{
				"start":	43.000224,
				"end":	44.00063,
				"seconds":	1.00040602684021,
				"bytes":	7864320,
				"bits_per_second":	62889025.367746048,
				"retransmits":	99,
				"omitted":	false,
				"sender":	true
			}
		}, {
			"streams":	[{
					"socket":	5,
					"start":	44.00063,
					"end":	45.000325,
					"seconds":	0.99969500303268433,
					"bytes":	6553600,
					"bits_per_second":	52444795.503580086,
					"retransmits":	0,
					"snd_cwnd":	622440,
					"rtt":	67710,
					"rttvar":	726,
					"pmtu":	1420,
					"omitted":	false,
					"sender":	true
				}],
			"sum":	{
				"start":	44.00063,
				"end":	45.000325,
				"seconds":	0.99969500303268433,
				"bytes":	6553600,
				"bits_per_second":	52444795.503580086,
				"retransmits":	0,
				"omitted":	false,
				"sender":	true
			}
		}, {
			"streams":	[{
					"socket":	5,
					"start":	45.000325,
					"end":	46.000142,
					"seconds":	0.99981701374053955,
					"bytes":	7864320,
					"bits_per_second":	62926074.607014865,
					"retransmits":	0,
					"snd_cwnd":	678528,
					"rtt":	73603,
					"rttvar":	1220,
					"pmtu":	1420,
					"omitted":	false,
					"sender":	true
				}],
			"sum":	{
				"start":	45.000325,
				"end":	46.000142,
				"seconds":	0.99981701374053955,
				"bytes":	7864320,
				"bits_per_second":	62926074.607014865,
				"retransmits":	0,
				"omitted":	false,
				"sender":	true
			}
		}, {
			"streams":	[{
					"socket":	5,
					"start":	46.000142,
					"end":	47.001718,
					"seconds":	1.0015759468078613,
					"bytes":	7864320,
					"bits_per_second":	62815566.0092637,
					"retransmits":	0,
					"snd_cwnd":	718200,
					"rtt":	71428,
					"rttvar":	1481,
					"pmtu":	1420,
					"omitted":	false,
					"sender":	true
				}],
			"sum":	{
				"start":	46.000142,
				"end":	47.001718,
				"seconds":	1.0015759468078613,
				"bytes":	7864320,
				"bits_per_second":	62815566.0092637,
				"retransmits":	0,
				"omitted":	false,
				"sender":	true
			}
		}, {
			"streams":	[{
					"socket":	5,
					"start":	47.001718,
					"end":	48.000512,
					"seconds":	0.99879401922225952,
					"bytes":	6553600,
					"bits_per_second":	52492104.468972728,
					"retransmits":	44,
					"snd_cwnd":	547200,
					"rtt":	72434,
					"rttvar":	550,
					"pmtu":	1420,
					"omitted":	false,
					"sender":	true
				}],
			"sum":	{
				"start":	47.001718,
				"end":	48.000512,
				"seconds":	0.99879401922225952,
				"bytes":	6553600,
				"bits_per_second":	52492104.468972728,
				"retransmits":	44,
				"omitted":	false,
				"sender":	true
			}
		}, {
			"streams":	[{
					"socket":	5,
					"start":	48.000512,
					"end":	49.000906,
					"seconds":	1.0003939867019653,
					"bytes":	6553600,
					"bits_per_second":	52408151.8850827,
					"retransmits":	0,
					"snd_cwnd":	580032,
					"rtt":	84143,
					"rttvar":	1594,
					"pmtu":	1420,
					"omitted":	false,
					"sender":	true
				}],
			"sum":	{
				"start":	48.000512,
				"end":	49.000906,
				"seconds":	1.0003939867019653,
				"bytes":	6553600,
				"bits_per_second":	52408151.8850827,
				"retransmits":	0,
				"omitted":	false,
				"sender":	true
			}
		}, {
			"streams":	[{
					"socket":	5,
					"start":	49.000906,
					"end":	50.000781,
					"seconds":	0.999875009059906,
					"bytes":	6553600,
					"bits_per_second":	52435353.944183648,
					"retransmits":	0,
					"snd_cwnd":	599184,
					"rtt":	69407,
					"rttvar":	1153,
					"pmtu":	1420,
					"omitted":	false,
					"sender":	true
				}],
			"sum":	{
				"start":	49.000906,
				"end":	50.000781,
				"seconds":	0.999875009059906,
				"bytes":	6553600,
				"bits_per_second":	52435353.944183648,
				"retransmits":	0,
				"omitted":	false,
				"sender":	true
			}
		}, {
			"streams":	[{
					"socket":	5,
					"start":	50.000781,
					"end":	51.000397,
					"seconds":	0.999616026878357,
					"bytes":	7864320,
					"bits_per_second":	62938726.779393725,
					"retransmits":	0,
					"snd_cwnd":	610128,
					"rtt":	74071,
					"rttvar":	283,
					"pmtu":	1420,
					"omitted":	false,
					"sender":	true
				}],
			"sum":	{
				"start":	50.000781,
				"end":	51.000397,
				"seconds":	0.999616026878357,
				"bytes":	7864320,
				"bits_per_second":	62938726.779393725,
				"retransmits":	0,
				"omitted":	false,
				"sender":	true
			}
		}, {
			"streams":	[{
					"socket":	5,
					"start":	51.000397,
					"end":	52.000745,
					"seconds":	1.0003479719161987,
					"bytes":	6553600,
					"bits_per_second":	52410562.596104383,
					"retransmits":	0,
					"snd_cwnd":	612864,
					"rtt":	71589,
					"rttvar":	218,
					"pmtu":	1420,
					"omitted":	false,
					"sender":	true
				}],
			"sum":	{
				"start":	51.000397,
				"end":	52.000745,
				"seconds":	1.0003479719161987,
				"bytes":	6553600,
				"bits_per_second":	52410562.596104383,
				"retransmits":	0,
				"omitted":	false,
				"sender":	true
			}
		}, {
			"streams":	[{
					"socket":	5,
					"start":	52.000745,
					"end":	53.001062,
					"seconds":	1.0003169775009155,
					"bytes":	7864320,
					"bits_per_second":	62894623.819320731,
					"retransmits":	0,
					"snd_cwnd":	612864,
					"rtt":	69479,
					"rttvar":	943,
					"pmtu":	1420,
					"omitted":	false,
					"sender":	true
				}],
			"sum":	{
				"start":	52.000745,
				"end":	53.001062,
				"seconds":	1.0003169775009155,
				"bytes":	7864320,
				"bits_per_second":	62894623.819320731,
				"retransmits":	0,
				"omitted":	false,
				"sender":	true
			}
		}, {
			"streams":	[{
					"socket":	5,
					"start":	53.001062,
					"end":	54.000658,
					"seconds":	0.9995959997177124,
					"bytes":	7864320,
					"bits_per_second":	62939987.7728274,
					"retransmits":	0,
					"snd_cwnd":	612864,
					"rtt":	77456,
					"rttvar":	4554,
					"pmtu":	1420,
					"omitted":	false,
					"sender":	true
				}],
			"sum":	{
				"start":	53.001062,
				"end":	54.000658,
				"seconds":	0.9995959997177124,
				"bytes":	7864320,
				"bits_per_second":	62939987.7728274,
				"retransmits":	0,
				"omitted":	false,
				"sender":	true
			}
		}, {
			"streams":	[{
					"socket":	5,
					"start":	54.000658,
					"end":	55.000387,
					"seconds":	0.9997289776802063,
					"bytes":	7864320,
					"bits_per_second":	62931615.872522138,
					"retransmits":	0,
					"snd_cwnd":	616968,
					"rtt":	74275,
					"rttvar":	4734,
					"pmtu":	1420,
					"omitted":	false,
					"sender":	true
				}],
			"sum":	{
				"start":	54.000658,
				"end":	55.000387,
				"seconds":	0.9997289776802063,
				"bytes":	7864320,
				"bits_per_second":	62931615.872522138,
				"retransmits":	0,
				"omitted":	false,
				"sender":	true
			}
		}, {
			"streams":	[{
					"socket":	5,
					"start":	55.000387,
					"end":	56.001445,
					"seconds":	1.0010579824447632,
					"bytes":	6553600,
					"bits_per_second":	52373389.872941688,
					"retransmits":	0,
					"snd_cwnd":	627912,
					"rtt":	89138,
					"rttvar":	2786,
					"pmtu":	1420,
					"omitted":	false,
					"sender":	true
				}],
			"sum":	{
				"start":	55.000387,
				"end":	56.001445,
				"seconds":	1.0010579824447632,
				"bytes":	6553600,
				"bits_per_second":	52373389.872941688,
				"retransmits":	0,
				"omitted":	false,
				"sender":	true
			}
		}, {
			"streams":	[{
					"socket":	5,
					"start":	56.001445,
					"end":	57.000151,
					"seconds":	0.99870598316192627,
					"bytes":	7864320,
					"bits_per_second":	62996077.985646032,
					"retransmits":	0,
					"snd_cwnd":	648432,
					"rtt":	71749,
					"rttvar":	1467,
					"pmtu":	1420,
					"omitted":	false,
					"sender":	true
				}],
			"sum":	{
				"start":	56.001445,
				"end":	57.000151,
				"seconds":	0.99870598316192627,
				"bytes":	7864320,
				"bits_per_second":	62996077.985646032,
				"retransmits":	0,
				"omitted":	false,
				"sender":	true
			}
		}, {
			"streams":	[{
					"socket":	5,
					"start":	57.000151,
					"end":	58.003179,
					"seconds":	1.0030280351638794,
					"bytes":	3932160,
					"bits_per_second":	31362313.810959794,
					"retransmits":	1,
					"snd_cwnd":	322848,
					"rtt":	67012,
					"rttvar":	1243,
					"pmtu":	1420,
					"omitted":	false,
					"sender":	true
				}],
			"sum":	{
				"start":	57.000151,
				"end":	58.003179,
				"seconds":	1.0030280351638794,
				"bytes":	3932160,
				"bits_per_second":	31362313.810959794,
				"retransmits":	1,
				"omitted":	false,
				"sender":	true
			}
		}, {
			"streams":	[{
					"socket":	5,
					"start":	58.003179,
					"end":	59.000582,
					"seconds":	0.99740302562713623,
					"bytes":	5242880,
					"bits_per_second":	42052248.611966573,
					"retransmits":	0,
					"snd_cwnd":	428184,
					"rtt":	71979,
					"rttvar":	1712,
					"pmtu":	1420,
					"omitted":	false,
					"sender":	true
				}],
			"sum":	{
				"start":	58.003179,
				"end":	59.000582,
				"seconds":	0.99740302562713623,
				"bytes":	5242880,
				"bits_per_second":	42052248.611966573,
				"retransmits":	0,
				"omitted":	false,
				"sender":	true
			}
		}, {
			"streams":	[{
					"socket":	5,
					"start":	59.000582,
					"end":	60.000208,
					"seconds":	0.99962598085403442,
					"bytes":	5242880,
					"bits_per_second":	41958733.3696207,
					"retransmits":	0,
					"snd_cwnd":	506160,
					"rtt":	71211,
					"rttvar":	2038,
					"pmtu":	1420,
					"omitted":	false,
					"sender":	true
				}],
			"sum":	{
				"start":	59.000582,
				"end":	60.000208,
				"seconds":	0.99962598085403442,
				"bytes":	5242880,
				"bits_per_second":	41958733.3696207,
				"retransmits":	0,
				"omitted":	false,
				"sender":	true
			}
		}],
	"end":	{
		"streams":	[{
				"sender":	{
					"socket":	5,
					"start":	0,
					"end":	60.000208,
					"seconds":	60.000208,
					"bytes":	420987008,
					"bits_per_second":	56131406.477790877,
					"retransmits":	400,
					"max_snd_cwnd":	764712,
					"max_rtt":	89138,
					"min_rtt":	66008,
					"mean_rtt":	73240,
					"sender":	true
				},
				"receiver":	{
					"socket":	5,
					"start":	0,
					"end":	60.094819,
					"seconds":	60.000208,
					"bytes":	417988608,
					"bits_per_second":	55643879.449907318,
					"sender":	true
				}
			}],
		"sum_sent":	{
			"start":	0,
			"end":	60.000208,
			"seconds":	60.000208,
			"bytes":	420987008,
			"bits_per_second":	56131406.477790877,
			"retransmits":	400,
			"sender":	true
		},
		"sum_received":	{
			"start":	0,
			"end":	60.094819,
			"seconds":	60.094819,
			"bytes":	417988608,
			"bits_per_second":	55643879.449907318,
			"sender":	true
		},
		"cpu_utilization_percent":	{
			"host_total":	0.478465682919573,
			"host_user":	0.0027884294550281218,
			"host_system":	0.47567890930151346,
			"remote_total":	2.4261969758095483,
			"remote_user":	0.23261948587350936,
			"remote_system":	2.193578231208607
		},
		"sender_tcp_congestion":	"cubic",
		"receiver_tcp_congestion":	"cubic"
	}
}
