[
  {
    "ts": 1774659424.5923283,
    "cpu_percent": 1.1,
    "mem_percent": 21.0
  },
  {
    "ts": 1774659425.5945501,
    "cpu_percent": 0.0,
    "mem_percent": 21.0
  },
  {
    "ts": 1774659426.5973825,
    "cpu_percent": 0.0,
    "mem_percent": 21.0
  },
  {
    "ts": 1774659427.599446,
    "cpu_percent": 0.0,
    "mem_percent": 21.0
  },
  {
    "ts": 1774659428.6014428,
    "cpu_percent": 0.0,
    "mem_percent": 21.0
  },
  {
    "ts": 1774659429.6038084,
    "cpu_percent": 0.0,
    "mem_percent": 21.0
  },
  {
    "ts": 1774659430.605518,
    "cpu_percent": 2.1,
    "mem_percent": 21.0
  },
  {
    "ts": 1774659431.6067586,
    "cpu_percent": 0.0,
    "mem_percent": 21.0
  },
  {
    "ts": 1774659432.6075463,
    "cpu_percent": 0.0,
    "mem_percent": 21.0
  },
  {
    "ts": 1774659433.6118522,
    "cpu_percent": 10.8,
    "mem_percent": 21.0
  },
  {
    "ts": 1774659434.6141212,
    "cpu_percent": 0.0,
    "mem_percent": 21.0
  },
  {
    "ts": 1774659435.6172826,
    "cpu_percent": 0.0,
    "mem_percent": 21.0
  },
  {
    "ts": 1774659436.7791097,
    "cpu_percent": 0.9,
    "mem_percent": 21.0
  },
  {
    "ts": 1774659437.7823074,
    "cpu_percent": 0.0,
    "mem_percent": 21.0
  },
  {
    "ts": 1774659438.783684,
    "cpu_percent": 0.0,
    "mem_percent": 21.0
  },
  {
    "ts": 1774659439.785253,
    "cpu_percent": 0.0,
    "mem_percent": 21.0
  },
  {
    "ts": 1774659440.7873626,
    "cpu_percent": 0.0,
    "mem_percent": 21.0
  },
  {
    "ts": 1774659441.789098,
    "cpu_percent": 0.5,
    "mem_percent": 21.0
  },
  {
    "ts": 1774659442.7916954,
    "cpu_percent": 0.0,
    "mem_percent": 21.0
  },
  {
    "ts": 1774659443.7926805,
    "cpu_percent": 0.5,
    "mem_percent": 21.0
  },
  {
    "ts": 1774659444.7949874,
    "cpu_percent": 0.0,
    "mem_percent": 21.0
  },
  {
    "ts": 1774659445.7975023,
    "cpu_percent": 0.0,
    "mem_percent": 21.0
  },
  {
    "ts": 1774659446.7991188,
    "cpu_percent": 0.0,
    "mem_percent": 21.0
  },
  {
    "ts": 1774659447.8540537,
    "cpu_percent": 0.0,
    "mem_percent": 21.0
  },
  {
    "ts": 1774659448.89082,
    "cpu_percent": 1.4,
    "mem_percent": 21.0
  },
  {
    "ts": 1774659449.8916311,
    "cpu_percent": 0.0,
    "mem_percent": 21.0
  },
  {
    "ts": 1774659450.8924787,
    "cpu_percent": 0.0,
    "mem_percent": 21.0
  },
  {
    "ts": 1774659451.8940542,
    "cpu_percent": 0.0,
    "mem_percent": 21.0
  },
  {
    "ts": 1774659452.895728,
    "cpu_percent": 0.0,
    "mem_percent": 21.0
  },
  {
    "ts": 1774659453.8966541,
    "cpu_percent": 0.0,
    "mem_percent": 21.0
  },
  {
    "ts": 1774659454.8988314,
    "cpu_percent": 0.0,
    "mem_percent": 21.0
  },
  {
    "ts": 1774659455.900627,
    "cpu_percent": 0.0,
    "mem_percent": 21.0
  },
  {
    "ts": 1774659456.9021533,
    "cpu_percent": 0.5,
    "mem_percent": 21.0
  },
  {
    "ts": 1774659457.9052827,
    "cpu_percent": 0.0,
    "mem_percent": 21.0
  },
  {
    "ts": 1774659458.9069097,
    "cpu_percent": 0.0,
    "mem_percent": 21.0
  },
  {
    "ts": 1774659459.9167857,
    "cpu_percent": 0.0,
    "mem_percent": 21.0
  },
  {
    "ts": 1774659461.1064837,
    "cpu_percent": 0.4,
    "mem_percent": 21.0
  },
  {
    "ts": 1774659462.108858,
    "cpu_percent": 0.0,
    "mem_percent": 21.0
  },
  {
    "ts": 1774659463.1108913,
    "cpu_percent": 0.0,
    "mem_percent": 21.0
  },
  {
    "ts": 1774659464.1132855,
    "cpu_percent": 0.0,
    "mem_percent": 21.0
  },
  {
    "ts": 1774659465.114783,
    "cpu_percent": 0.0,
    "mem_percent": 21.0
  },
  {
    "ts": 1774659466.117147,
    "cpu_percent": 0.0,
    "mem_percent": 21.0
  },
  {
    "ts": 1774659467.1188672,
    "cpu_percent": 0.5,
    "mem_percent": 21.0
  },
  {
    "ts": 1774659468.1207888,
    "cpu_percent": 0.0,
    "mem_percent": 21.0
  },
  {
    "ts": 1774659469.1230018,
    "cpu_percent": 0.0,
    "mem_percent": 21.0
  },
  {
    "ts": 1774659470.1248362,
    "cpu_percent": 0.0,
    "mem_percent": 21.0
  },
  {
    "ts": 1774659471.1267643,
    "cpu_percent": 0.0,
    "mem_percent": 21.0
  },
  {
    "ts": 1774659472.1505733,
    "cpu_percent": 0.0,
    "mem_percent": 21.0
  },
  {
    "ts": 1774659473.2365446,
    "cpu_percent": 0.0,
    "mem_percent": 21.0
  },
  {
    "ts": 1774659474.2377825,
    "cpu_percent": 0.0,
    "mem_percent": 21.0
  },
  {
    "ts": 1774659475.2389874,
    "cpu_percent": 0.0,
    "mem_percent": 21.0
  },
  {
    "ts": 1774659476.2409923,
    "cpu_percent": 0.0,
    "mem_percent": 21.0
  },
  {
    "ts": 1774659477.2427094,
    "cpu_percent": 0.0,
    "mem_percent": 21.0
  },
  {
    "ts": 1774659478.2439008,
    "cpu_percent": 0.5,
    "mem_percent": 21.0
  },
  {
    "ts": 1774659479.2451322,
    "cpu_percent": 0.0,
    "mem_percent": 21.0
  },
  {
    "ts": 1774659480.2475607,
    "cpu_percent": 0.0,
    "mem_percent": 21.0
  },
  {
    "ts": 1774659481.2498906,
    "cpu_percent": 0.0,
    "mem_percent": 21.0
  },
  {
    "ts": 1774659482.2516649,
    "cpu_percent": 0.0,
    "mem_percent": 21.0
  },
  {
    "ts": 1774659483.2530637,
    "cpu_percent": 0.0,
    "mem_percent": 21.0
  },
  {
    "ts": 1774659484.3058863,
    "cpu_percent": 0.5,
    "mem_percent": 21.0
  }
]