[
  {
    "ts": 1774877211.1554732,
    "cpu_percent": 95.5,
    "mem_percent": 20.6
  },
  {
    "ts": 1774877212.1579041,
    "cpu_percent": 100.0,
    "mem_percent": 20.6
  },
  {
    "ts": 1774877213.1737301,
    "cpu_percent": 100.0,
    "mem_percent": 20.6
  },
  {
    "ts": 1774877214.178616,
    "cpu_percent": 100.0,
    "mem_percent": 20.6
  },
  {
    "ts": 1774877215.1845486,
    "cpu_percent": 100.0,
    "mem_percent": 20.6
  },
  {
    "ts": 1774877216.193872,
    "cpu_percent": 100.0,
    "mem_percent": 20.6
  },
  {
    "ts": 1774877217.1964316,
    "cpu_percent": 100.0,
    "mem_percent": 20.6
  },
  {
    "ts": 1774877218.1977103,
    "cpu_percent": 100.0,
    "mem_percent": 20.6
  },
  {
    "ts": 1774877219.2061036,
    "cpu_percent": 100.0,
    "mem_percent": 20.6
  },
  {
    "ts": 1774877220.394582,
    "cpu_percent": 100.0,
    "mem_percent": 20.6
  },
  {
    "ts": 1774877221.4048264,
    "cpu_percent": 100.0,
    "mem_percent": 20.6
  },
  {
    "ts": 1774877222.4071178,
    "cpu_percent": 100.0,
    "mem_percent": 20.6
  },
  {
    "ts": 1774877223.4088516,
    "cpu_percent": 100.0,
    "mem_percent": 20.6
  },
  {
    "ts": 1774877224.418985,
    "cpu_percent": 100.0,
    "mem_percent": 20.6
  },
  {
    "ts": 1774877225.424115,
    "cpu_percent": 100.0,
    "mem_percent": 20.6
  },
  {
    "ts": 1774877226.6138065,
    "cpu_percent": 100.0,
    "mem_percent": 20.6
  },
  {
    "ts": 1774877227.7555346,
    "cpu_percent": 100.0,
    "mem_percent": 20.6
  },
  {
    "ts": 1774877228.7583296,
    "cpu_percent": 100.0,
    "mem_percent": 20.6
  },
  {
    "ts": 1774877229.7662861,
    "cpu_percent": 100.0,
    "mem_percent": 20.6
  },
  {
    "ts": 1774877230.775456,
    "cpu_percent": 100.0,
    "mem_percent": 20.6
  },
  {
    "ts": 1774877231.7793708,
    "cpu_percent": 100.0,
    "mem_percent": 20.6
  },
  {
    "ts": 1774877232.786246,
    "cpu_percent": 100.0,
    "mem_percent": 20.6
  },
  {
    "ts": 1774877233.7894738,
    "cpu_percent": 100.0,
    "mem_percent": 20.6
  },
  {
    "ts": 1774877234.7909582,
    "cpu_percent": 100.0,
    "mem_percent": 20.6
  },
  {
    "ts": 1774877235.8756082,
    "cpu_percent": 100.0,
    "mem_percent": 20.6
  },
  {
    "ts": 1774877236.894085,
    "cpu_percent": 100.0,
    "mem_percent": 20.6
  },
  {
    "ts": 1774877237.9131877,
    "cpu_percent": 98.0,
    "mem_percent": 20.6
  },
  {
    "ts": 1774877238.9177806,
    "cpu_percent": 100.0,
    "mem_percent": 20.6
  },
  {
    "ts": 1774877239.9326406,
    "cpu_percent": 100.0,
    "mem_percent": 20.6
  },
  {
    "ts": 1774877241.101656,
    "cpu_percent": 100.0,
    "mem_percent": 20.6
  },
  {
    "ts": 1774877242.1167321,
    "cpu_percent": 98.6,
    "mem_percent": 20.6
  },
  {
    "ts": 1774877243.125687,
    "cpu_percent": 100.0,
    "mem_percent": 20.6
  },
  {
    "ts": 1774877244.1323106,
    "cpu_percent": 100.0,
    "mem_percent": 20.6
  },
  {
    "ts": 1774877245.1415884,
    "cpu_percent": 100.0,
    "mem_percent": 20.6
  },
  {
    "ts": 1774877246.1470828,
    "cpu_percent": 100.0,
    "mem_percent": 20.6
  },
  {
    "ts": 1774877247.1841602,
    "cpu_percent": 100.0,
    "mem_percent": 20.6
  },
  {
    "ts": 1774877248.1860404,
    "cpu_percent": 100.0,
    "mem_percent": 20.6
  },
  {
    "ts": 1774877249.3140037,
    "cpu_percent": 100.0,
    "mem_percent": 20.6
  },
  {
    "ts": 1774877250.3349419,
    "cpu_percent": 100.0,
    "mem_percent": 20.6
  },
  {
    "ts": 1774877251.3375177,
    "cpu_percent": 100.0,
    "mem_percent": 20.6
  },
  {
    "ts": 1774877252.3757222,
    "cpu_percent": 100.0,
    "mem_percent": 20.6
  },
  {
    "ts": 1774877253.400853,
    "cpu_percent": 100.0,
    "mem_percent": 20.6
  },
  {
    "ts": 1774877254.4158878,
    "cpu_percent": 100.0,
    "mem_percent": 20.6
  },
  {
    "ts": 1774877255.4225295,
    "cpu_percent": 100.0,
    "mem_percent": 20.6
  },
  {
    "ts": 1774877256.5586174,
    "cpu_percent": 100.0,
    "mem_percent": 20.6
  },
  {
    "ts": 1774877257.5725317,
    "cpu_percent": 100.0,
    "mem_percent": 20.6
  },
  {
    "ts": 1774877258.5776625,
    "cpu_percent": 13.0,
    "mem_percent": 20.6
  },
  {
    "ts": 1774877259.5793378,
    "cpu_percent": 0.5,
    "mem_percent": 20.6
  },
  {
    "ts": 1774877260.581938,
    "cpu_percent": 0.0,
    "mem_percent": 20.6
  },
  {
    "ts": 1774877261.5845463,
    "cpu_percent": 1.1,
    "mem_percent": 20.6
  },
  {
    "ts": 1774877262.5882287,
    "cpu_percent": 0.5,
    "mem_percent": 20.6
  },
  {
    "ts": 1774877263.591822,
    "cpu_percent": 0.0,
    "mem_percent": 20.6
  },
  {
    "ts": 1774877264.5955088,
    "cpu_percent": 0.0,
    "mem_percent": 20.6
  },
  {
    "ts": 1774877265.5984142,
    "cpu_percent": 0.5,
    "mem_percent": 20.6
  },
  {
    "ts": 1774877266.6033654,
    "cpu_percent": 0.0,
    "mem_percent": 20.6
  },
  {
    "ts": 1774877267.6070592,
    "cpu_percent": 0.0,
    "mem_percent": 20.6
  },
  {
    "ts": 1774877268.6101294,
    "cpu_percent": 0.0,
    "mem_percent": 20.6
  },
  {
    "ts": 1774877269.6129348,
    "cpu_percent": 1.1,
    "mem_percent": 20.6
  },
  {
    "ts": 1774877270.6170037,
    "cpu_percent": 0.0,
    "mem_percent": 20.6
  }
]